{
  "modURL": "https://7daystodiemods.com/skull-lights/",
  "modCreatedTime": "2020-08-22T20:56:00+00:00",
  "modLastUpdatedTime": "2020-08-22T20:57:13+00:00",
  "modName": "Skull Lights",
  "modImages": [
    "https://7daystodiemods.com/wp-content/uploads/2020/08/7-days-to-die-skull-lights-additional-screenshot.jpg"
  ],
  "modShortDescription": "Skulls that putt off multi color lights. A crafting station to make the Skull_Lamps on. The crafting station schematics is found loot item.",
  "modDescription": "Skulls that putt off multi color [lights](https://7daystodiemods.com/tag/7-days-to-die-lights/). A crafting station to make the Skull\\_Lamps on. The crafting station schematics is found loot item.\n\n## Changelog\n\nUpdated to A19 Stable version.\n\n**[Download](https://gitlab.com/Grindhouse-Farmlife/skull-lights/-/archive/master/skull-lights-master.zip)**\n\n**Credits:** [skullman678](https://7daystodiemods.com/tag/skullman678/)",
  "modDownloadURLs": [
    {
      "Info": "Download",
      "URL": "https://gitlab.com/Grindhouse-Farmlife/skull-lights/-/archive/master/skull-lights-master.zip",
      "Version": "v19"
    }
  ],
  "modPotentialyOutdated": true,
  "modAuthors": [
    "skullman678"
  ],
  "modTags": [
    "7 days to die lights",
    "skullman678"
  ]
}